{
  "swagger": "2.0",
  "info": {
    "title": "MAC Address",
    "version": "2021-12-20",
    "license": {
      "name": "OCF Data Model License",
      "url": "https://github.com/openconnectivityfoundation/core/blob/e28a9e0a92e17042ba3e83661e4c0fbce8bdc4ba/LICENSE.md",
      "x-copyright": "copyright 2021 Open Connectivity Foundation, Inc. All rights reserved."
    },
    "termsOfService": "https://openconnectivityfoundation.github.io/core/DISCLAIMER.md"
  },
  "schemes": ["http"],
  "consumes": ["application/json"],
  "produces": ["application/json"],
  "paths": {
  }
}
