{
  "swagger": "2.0",
  "info": {
    "title": "Router",
    "version": "2021-12-20",
    "license": {
      "name": "OCF Data Model License",
      "url": "https://github.com/openconnectivityfoundation/core/blob/e28a9e0a92e17042ba3e83661e4c0fbce8bdc4ba/LICENSE.md",
      "x-copyright": "copyright 2021 Open Connectivity Foundation, Inc. All rights reserved."
    },
    "termsOfService": "https://openconnectivityfoundation.github.io/core/DISCLAIMER.md"
  },
  "schemes": ["http"],
  "consumes": ["application/json"],
  "produces": ["application/json"],
  "paths": {
    "/RoutesResURI" : {
      "get": {
        "description": "This Resource describes a network route.\n",
        "parameters": [
          {"$ref": "#/parameters/interface"}
        ],
        "responses": {
          "200": {
            "description" : "",
            "x-example":
            {
              "rt": ["oic.r.network.route"],
              "if": ["oic.if.a", "oic.if.baseline"],
              "value": false
            },
            "schema": { "$ref": "#/definitions/NetworkRoute" }
          }
        }
      },
      "post": {
        "description": "",
        "parameters": [
          {"$ref": "#/parameters/interface"},
          {
            "name": "body",
            "in": "body",
            "required": true,
            "schema": { "$ref": "#/definitions/NetworkRoute" },
            "x-example":
            {
              "value": true
            }
          }
        ],
        "responses": {
          "200": {
            "description" : "",
            "x-example":
            {
              "value": true
            },
            "schema": { "$ref": "#/definitions/NetworkRoute" }
          }
        }
      }
    }
  },
  "parameters": {
    "interface" : {
      "in": "query",
      "name": "if",
      "type": "string",
      "enum": ["oic.if.a", "oic.if.baseline"]
    }
  },
  "definitions": {
    "NetworkRoute" : {
      "properties": {
        "rt": {
          "description": "The Resource Type.",
          "items": {
            "enum": ["oic.r.network.route"],
            "maxLength": 64,
            "type": "string"
          },
          "minItems": 1,
          "uniqueItems": true,
          "readOnly": true,
          "type": "array"
        },
        "IPAddress": {
          "description": "The IP address of the network interface",
          "type": "string",
          "maxLength": 64
        },
        "Netmask": {
          "description" : "The subnet mask of for the IP address",
          "type": "string",
          "maxLength": 64
        },
        "Gateway": {
          "description": "The gateway for this route",
          "type": "string",
          "maxLength": 64
        },
        "metric": {
          "description": "The metric helps the router choose the best route",
          "type": "integer"
        },
        "interface": {

        },
        "n": {
          "$ref": "https://openconnectivityfoundation.github.io/core/schemas/oic.common.properties.core-schema.json#/definitions/n"
        },
        "id": {
          "$ref": "https://openconnectivityfoundation.github.io/core/schemas/oic.common.properties.core-schema.json#/definitions/id"
        },
        "if": {
          "description": "The OCF Interface set supported by this Resource.",
          "items": {
            "enum": [
              "oic.if.a",
              "oic.if.baseline"
            ],
            "type": "string"
          },
          "minItems": 2,
          "uniqueItems": true,
          "readOnly": true,
          "type": "array"
        }
      },
      "type": "object",
      "required": ["IPAddress","Netmask","Gateway"]
    }
  }
}
